evidentialreasoning/ER.py
evidentialreasoning/__init__.py
evidentialreasoning-1.0.4.dist-info/LICENSE
evidentialreasoning-1.0.4.dist-info/LICENSE.txt
evidentialreasoning-1.0.4.dist-info/METADATA
evidentialreasoning-1.0.4.dist-info/WHEEL
evidentialreasoning-1.0.4.dist-info/top_level.txt
evidentialreasoning-1.0.4.dist-info/RECORD
