Metadata-Version: 2.1
Name: evidentialreasoning
Version: 1.0.4
Summary: A python package for evidential reasoning (ER) approach
Home-page: https://github.com/
Author: nmtoan91
Author-email: toan_stt@yahoo.com
Classifier: Programming Language :: Python :: 3
Classifier: License :: OSI Approved :: MIT License
Classifier: Operating System :: OS Independent
Requires-Python: >=3.6
License-File: LICENSE
License-File: LICENSE.txt
